docker_copyedit-1.5.1222.data/scripts/docker-copyedit.py
docker_copyedit-1.5.1222.data/scripts/docker-copyedit.pyi
docker_copyedit1/EUPL-LICENSE.md
docker_copyedit1/RELEASENOTES.md
docker_copyedit1/docker_copyedit.py
docker_copyedit1/docker_copyedit_tests.py
docker_copyedit1/py.typed
docker_copyedit-1.5.1222.dist-info/METADATA
docker_copyedit-1.5.1222.dist-info/WHEEL
docker_copyedit-1.5.1222.dist-info/entry_points.txt
docker_copyedit-1.5.1222.dist-info/top_level.txt
docker_copyedit-1.5.1222.dist-info/RECORD
