Metadata-Version: 2.2
Name: docker_copyedit
Version: 1.5.1222
Summary: edit docker image metadata (including remove docker volume settings)
Author-email: "Guido U. Draheim" <Guido.Draheim@gmx.de>
License-Expression: EUPL-1.2
Project-URL: homepage, https://github.com/gdraheim/docker-copyedit
Provides-Extra: dev
Requires-Dist: build; extra == "dev"
